plantuml2freemind/__init__.py
plantuml2freemind/__main__.py
plantuml2freemind/cli.py
plantuml2freemind/cli_commands.py
plantuml2freemind/custom_types.py
plantuml2freemind/generators/__init__.py
plantuml2freemind/generators/freemind.py
plantuml2freemind/generators/mapping.py
plantuml2freemind/generators/markdown.py
plantuml2freemind/generators/plantuml.py
plantuml2freemind/generators/yaml.py
plantuml2freemind/parsers/__init__.py
plantuml2freemind/parsers/mapping.py
plantuml2freemind/parsers/plantuml.py
plantuml2freemind/parsers/yaml.py
plantuml2freemind-0.8.2.dist-info/entry_points.txt
plantuml2freemind-0.8.2.dist-info/LICENSE
plantuml2freemind-0.8.2.dist-info/WHEEL
plantuml2freemind-0.8.2.dist-info/METADATA
plantuml2freemind-0.8.2.dist-info/RECORD
