Metadata-Version: 2.1
Name: plantuml2freemind
Version: 0.8.2
Summary: Converts plantuml mindmaps to freemind .mm files
Home-page: https://github.com/b0g3r/plantuml2freemind
License: MIT
Keywords: plantuml,freemind,puml,mm,converter
Author: Boger
Author-email: kotvberloge@gmail.com
Requires-Python: >=3.6,<4.0
Classifier: License :: OSI Approved :: MIT License
Classifier: Programming Language :: Python :: 3
Classifier: Programming Language :: Python :: 3.6
Classifier: Programming Language :: Python :: 3.7
Classifier: Programming Language :: Python :: 3.8
Classifier: Programming Language :: Python :: 3.9
Requires-Dist: attrs (>=19.3.0,<20.0.0)
Requires-Dist: cleo (>=0.8.1,<0.9.0)
Requires-Dist: pyyaml (>=5.3.1,<6.0.0)
Requires-Dist: typing-extensions (>=3.7.4,<4.0.0)
Project-URL: Repository, https://github.com/b0g3r/plantuml2freemind
